{
  "responses": [
    {
      "labelAnnotations": [
        {
          "mid": "/m/05qdh",
          "description": "painting",
          "score": 0.7283034
        },
        {
          "mid": "/m/0jjw",
          "description": "art",
          "score": 0.6648898
        }
      ],
      "safeSearchAnnotation": {
        "adult": "VERY_UNLIKELY",
        "spoof": "UNLIKELY",
        "medical": "VERY_UNLIKELY",
        "violence": "UNLIKELY"
      },
      "imagePropertiesAnnotation": {
        "dominantColors": {
          "colors": [
            {
              "color": {
                "red": 158,
                "green": 106,
                "blue": 56
              },
              "score": 0.09922857,
              "pixelFraction": 0.014112903
            },
            {
              "color": {
                "red": 214,
                "green": 191,
                "blue": 164
              },
              "score": 0.09145277,
              "pixelFraction": 0.021037867
            },
            {
              "color": {
                "red": 137,
                "green": 45,
                "blue": 26
              },
              "score": 0.074220195,
              "pixelFraction": 0.007626227
            },
            {
              "color": {
                "red": 85,
                "green": 44,
                "blue": 27
              },
              "score": 0.01922849,
              "pixelFraction": 0.022703366
            },
            {
              "color": {
                "red": 24,
                "green": 12,
                "blue": 5
              },
              "score": 0.0016993161,
              "pixelFraction": 0.63359046
            },
            {
              "color": {
                "red": 169,
                "green": 111,
                "blue": 41
              },
              "score": 0.073568515,
              "pixelFraction": 0.004908836
            },
            {
              "color": {
                "red": 195,
                "green": 144,
                "blue": 91
              },
              "score": 0.066356264,
              "pixelFraction": 0.0074509117
            },
            {
              "color": {
                "red": 126,
                "green": 76,
                "blue": 31
              },
              "score": 0.05713299,
              "pixelFraction": 0.010080645
            },
            {
              "color": {
                "red": 193,
                "green": 136,
                "blue": 63
              },
              "score": 0.054435425,
              "pixelFraction": 0.0030680224
            },
            {
              "color": {
                "red": 180,
                "green": 154,
                "blue": 129
              },
              "score": 0.050447863,
              "pixelFraction": 0.018495793
            }
          ]
        }
      },
      "cropHintsAnnotation": {
        "cropHints": [
          {
            "boundingPoly": {
              "vertices": [
                {},
                {
                  "x": 295
                },
                {
                  "x": 295,
                  "y": 367
                },
                {
                  "y": 367
                }
              ]
            },
            "confidence": 0.79999995,
            "importanceFraction": 0.98999995
          }
        ]
      },
      "webDetection": {
        "webEntities": [
          {
            "entityId": "/m/025zkyj",
            "score": 6.30672,
            "description": "Musée Fabre"
          },
          {
            "entityId": "/m/02x9xx",
            "score": 1.39544,
            "description": "Portrait of Madame X"
          },
          {
            "entityId": "/m/05qdh",
            "score": 1.0054057,
            "description": "Painting"
          },
          {
            "entityId": "/m/08b33",
            "score": 0.75646,
            "description": "18th century"
          },
          {
            "entityId": "/m/01dv4h",
            "score": 0.51255,
            "description": "Portrait"
          }
        ],
        "fullMatchingImages": [
          {
            "url": "http://f7.ifotki.info/org/583cc79fc62e66f831119156647495a85f482d75425424.jpg"
          },
          {
            "url": "http://www.fujibi.or.jp/assets/images/collection/base/01128.jpg"
          },
          {
            "url": "http://img-fotki.yandex.ru/get/5902/86441892.212/0_949a2_81b09372_orig.jpg"
          },
          {
            "url": "http://s42.radikal.ru/i097/1106/7c/e5a8a725033f.jpg"
          },
          {
            "url": "http://s018.radikal.ru/i526/1201/9d/15bbf6beac50t.jpg"
          }
        ],
        "partialMatchingImages": [
          {
            "url": "http://www.galeriepellatdevilledon.com/app/uploads/2015/05/DSCF7665_resultat.jpg"
          },
          {
            "url": "https://blog-001.west.edge.storage-yahoo.jp/res/blog-1f-9f/mitosya/folder/813919/19/21643619/img_9?1231037797"
          },
          {
            "url": "http://3.bp.blogspot.com/_8_ENa7sVpug/TIwOehHa92I/AAAAAAAAO_Q/xHAq-TyqKMM/s1600/m_crozat+1.jpg"
          },
          {
            "url": "http://www.wga.hu/art/a/aved/m_crozat.jpg"
          },
          {
            "url": "http://f7.ifotki.info/org/583cc79fc62e66f831119156647495a85f482d75425424.jpg"
          }
        ],
        "pagesWithMatchingImages": [
          {
            "url": "https://commons.wikimedia.org/wiki/File:Madame_Crozat.jpg"
          },
          {
            "url": "https://nga.gov.au/Exhibition/FrenchPainting/Detail.cfm?IRN=126540"
          },
          {
            "url": "http://www.wga.hu/html_m/a/aved/m_crozat.html"
          },
          {
            "url": "https://commons.wikimedia.org/wiki/File:Jacques_Aved_-_Madame_Crozat_-_WGA01064.jpg"
          },
          {
            "url": "https://nga.gov.au/Exhibition/FrenchPainting/Detail.cfm?IRN=126540&BioArtistIRN=25942&MnuID=4"
          }
        ],
        "visuallySimilarImages": [
          {
            "url": "https://s-media-cache-ak0.pinimg.com/736x/55/58/4c/55584c329d74f2692a78ac4d56eebc3b.jpg"
          },
          {
            "url": "http://www.youhuadaquan.org/images-small/Jacques%20Andre%20Joseph%20Aved/21668-Aved,%20Jacques-Andre-Joseph.jpg"
          },
          {
            "url": "http://www.artnet.de/WebServices/images/ll00093lld8BTGFgPjECfDrCWQFHPKcQyNC/jacques-andr%C3%A9-joseph-aved-portrait-de-madame-crozat.jpg"
          },
          {
            "url": "https://s-media-cache-ak0.pinimg.com/236x/d4/c0/67/d4c067ff2468f77f765571afc6ca33c3.jpg"
          },
          {
            "url": "http://3.bp.blogspot.com/_8_ENa7sVpug/TIwOfaafyzI/AAAAAAAAO_g/8z09D_dXQD0/s1600/Portrait+de+Marc+of+Villiers+2.jpg"
          }
        ]
      }
    }
  ]
}
