{
  "responses": [
    {
      "faceAnnotations": [
        {
          "boundingPoly": {
            "vertices": [
              {
                "x": 53,
                "y": 40
              },
              {
                "x": 215,
                "y": 40
              },
              {
                "x": 215,
                "y": 228
              },
              {
                "x": 53,
                "y": 228
              }
            ]
          },
          "fdBoundingPoly": {
            "vertices": [
              {
                "x": 60,
                "y": 91
              },
              {
                "x": 169,
                "y": 91
              },
              {
                "x": 169,
                "y": 200
              },
              {
                "x": 60,
                "y": 200
              }
            ]
          },
          "landmarks": [
            {
              "type": "LEFT_EYE",
              "position": {
                "x": 90.4854,
                "y": 123.00525,
                "z": 0.00023373422
              }
            },
            {
              "type": "RIGHT_EYE",
              "position": {
                "x": 133.30905,
                "y": 120.15603,
                "z": -26.1411
              }
            },
            {
              "type": "LEFT_OF_LEFT_EYEBROW",
              "position": {
                "x": 78.35502,
                "y": 112.76579,
                "z": 13.713651
              }
            },
            {
              "type": "RIGHT_OF_LEFT_EYEBROW",
              "position": {
                "x": 95.64953,
                "y": 110.18056,
                "z": -13.474399
              }
            },
            {
              "type": "LEFT_OF_RIGHT_EYEBROW",
              "position": {
                "x": 115.94926,
                "y": 109.05474,
                "z": -25.996696
              }
            },
            {
              "type": "RIGHT_OF_RIGHT_EYEBROW",
              "position": {
                "x": 148.13727,
                "y": 108.921074,
                "z": -29.299576
              }
            },
            {
              "type": "MIDPOINT_BETWEEN_EYES",
              "position": {
                "x": 105.44064,
                "y": 119.968094,
                "z": -21.22728
              }
            },
            {
              "type": "NOSE_TIP",
              "position": {
                "x": 97.93079,
                "y": 147.3252,
                "z": -35.980637
              }
            },
            {
              "type": "UPPER_LIP",
              "position": {
                "x": 103.97556,
                "y": 166.37738,
                "z": -27.784447
              }
            },
            {
              "type": "LOWER_LIP",
              "position": {
                "x": 106.047,
                "y": 180.59975,
                "z": -26.213293
              }
            },
            {
              "type": "MOUTH_LEFT",
              "position": {
                "x": 96.21468,
                "y": 174.02673,
                "z": -7.4616365
              }
            },
            {
              "type": "MOUTH_RIGHT",
              "position": {
                "x": 124.76578,
                "y": 172.96976,
                "z": -27.437353
              }
            },
            {
              "type": "MOUTH_CENTER",
              "position": {
                "x": 106.00341,
                "y": 172.9589,
                "z": -25.332785
              }
            },
            {
              "type": "NOSE_BOTTOM_RIGHT",
              "position": {
                "x": 118.86352,
                "y": 152.55093,
                "z": -27.307238
              }
            },
            {
              "type": "NOSE_BOTTOM_LEFT",
              "position": {
                "x": 96.01394,
                "y": 153.18578,
                "z": -13.07856
              }
            },
            {
              "type": "NOSE_BOTTOM_CENTER",
              "position": {
                "x": 103.19461,
                "y": 156.17912,
                "z": -27.092556
              }
            },
            {
              "type": "LEFT_EYE_TOP_BOUNDARY",
              "position": {
                "x": 88.24002,
                "y": 119.61804,
                "z": -2.2506204
              }
            },
            {
              "type": "LEFT_EYE_RIGHT_CORNER",
              "position": {
                "x": 98.43793,
                "y": 123.2371,
                "z": -4.778835
              }
            },
            {
              "type": "LEFT_EYE_BOTTOM_BOUNDARY",
              "position": {
                "x": 89.64239,
                "y": 126.793945,
                "z": -0.37931904
              }
            },
            {
              "type": "LEFT_EYE_LEFT_CORNER",
              "position": {
                "x": 84.05891,
                "y": 124.18889,
                "z": 9.173288
              }
            },
            {
              "type": "LEFT_EYE_PUPIL",
              "position": {
                "x": 88.68065,
                "y": 123.2143,
                "z": -0.3174616
              }
            },
            {
              "type": "RIGHT_EYE_TOP_BOUNDARY",
              "position": {
                "x": 130.05962,
                "y": 117.30103,
                "z": -28.024435
              }
            },
            {
              "type": "RIGHT_EYE_RIGHT_CORNER",
              "position": {
                "x": 142.14769,
                "y": 120.73165,
                "z": -26.813566
              }
            },
            {
              "type": "RIGHT_EYE_BOTTOM_BOUNDARY",
              "position": {
                "x": 132.12602,
                "y": 124.1991,
                "z": -26.200563
              }
            },
            {
              "type": "RIGHT_EYE_LEFT_CORNER",
              "position": {
                "x": 123.363235,
                "y": 121.75754,
                "z": -20.203873
              }
            },
            {
              "type": "RIGHT_EYE_PUPIL",
              "position": {
                "x": 131.51949,
                "y": 120.8346,
                "z": -26.830048
              }
            },
            {
              "type": "LEFT_EYEBROW_UPPER_MIDPOINT",
              "position": {
                "x": 85.12486,
                "y": 105.30564,
                "z": -1.9803036
              }
            },
            {
              "type": "RIGHT_EYEBROW_UPPER_MIDPOINT",
              "position": {
                "x": 130.453,
                "y": 102.81286,
                "z": -29.941612
              }
            },
            {
              "type": "LEFT_EAR_TRAGION",
              "position": {
                "x": 95.31145,
                "y": 153.28592,
                "z": 65.81179
              }
            },
            {
              "type": "RIGHT_EAR_TRAGION",
              "position": {
                "x": 190.22559,
                "y": 148.03188,
                "z": 7.3149304
              }
            },
            {
              "type": "FOREHEAD_GLABELLA",
              "position": {
                "x": 104.801575,
                "y": 108.911285,
                "z": -21.221525
              }
            },
            {
              "type": "CHIN_GNATHION",
              "position": {
                "x": 109.17411,
                "y": 206.36143,
                "z": -22.345888
              }
            },
            {
              "type": "CHIN_LEFT_GONION",
              "position": {
                "x": 89.31708,
                "y": 182.94806,
                "z": 43.266666
              }
            },
            {
              "type": "CHIN_RIGHT_GONION",
              "position": {
                "x": 175.04848,
                "y": 178.24255,
                "z": -9.639926
              }
            }
          ],
          "rollAngle": -0.033035092,
          "panAngle": -31.772646,
          "tiltAngle": 5.0845137,
          "detectionConfidence": 0.76995844,
          "landmarkingConfidence": 0.39498222,
          "joyLikelihood": "VERY_UNLIKELY",
          "sorrowLikelihood": "VERY_UNLIKELY",
          "angerLikelihood": "VERY_UNLIKELY",
          "surpriseLikelihood": "VERY_UNLIKELY",
          "underExposedLikelihood": "VERY_UNLIKELY",
          "blurredLikelihood": "VERY_UNLIKELY",
          "headwearLikelihood": "UNLIKELY"
        }
      ],
      "labelAnnotations": [
        {
          "mid": "/m/01g317",
          "description": "person",
          "score": 0.89858854
        },
        {
          "mid": "/m/0jjw",
          "description": "art",
          "score": 0.70329237
        },
        {
          "mid": "/m/01dv4h",
          "description": "portrait",
          "score": 0.7000812
        },
        {
          "mid": "/m/05qdh",
          "description": "painting",
          "score": 0.67252964
        },
        {
          "mid": "/m/067408",
          "description": "album cover",
          "score": 0.5592249
        }
      ],
      "textAnnotations": [
        {
          "locale": "ko",
          "description": "Tri\n낚\n",
          "boundingPoly": {
            "vertices": [
              {
                "x": 21,
                "y": 9
              },
              {
                "x": 283,
                "y": 9
              },
              {
                "x": 283,
                "y": 16
              },
              {
                "x": 21,
                "y": 16
              }
            ]
          }
        },
        {
          "description": "Tri",
          "boundingPoly": {
            "vertices": [
              {
                "x": 21,
                "y": 11
              },
              {
                "x": 33,
                "y": 11
              },
              {
                "x": 33,
                "y": 16
              },
              {
                "x": 21,
                "y": 16
              }
            ]
          }
        },
        {
          "description": "낚",
          "boundingPoly": {
            "vertices": [
              {
                "x": 277,
                "y": 9
              },
              {
                "x": 283,
                "y": 9
              },
              {
                "x": 283,
                "y": 16
              },
              {
                "x": 277,
                "y": 16
              }
            ]
          }
        }
      ],
      "safeSearchAnnotation": {
        "adult": "VERY_UNLIKELY",
        "spoof": "UNLIKELY",
        "medical": "VERY_UNLIKELY",
        "violence": "VERY_UNLIKELY"
      },
      "imagePropertiesAnnotation": {
        "dominantColors": {
          "colors": [
            {
              "color": {
                "red": 22,
                "green": 28,
                "blue": 35
              },
              "score": 0.7875422,
              "pixelFraction": 0.71686536
            },
            {
              "color": {
                "red": 214,
                "green": 185,
                "blue": 155
              },
              "score": 0.0031735427,
              "pixelFraction": 0.0031556801
            },
            {
              "color": {
                "red": 20,
                "green": 28,
                "blue": 41
              },
              "score": 0.08373118,
              "pixelFraction": 0.05645161
            },
            {
              "color": {
                "red": 42,
                "green": 44,
                "blue": 48
              },
              "score": 0.04675248,
              "pixelFraction": 0.051542778
            },
            {
              "color": {
                "red": 65,
                "green": 49,
                "blue": 34
              },
              "score": 0.013480757,
              "pixelFraction": 0.0087657785
            },
            {
              "color": {
                "red": 99,
                "green": 80,
                "blue": 62
              },
              "score": 0.010761563,
              "pixelFraction": 0.008941094
            },
            {
              "color": {
                "red": 108,
                "green": 76,
                "blue": 57
              },
              "score": 0.007925464,
              "pixelFraction": 0.015164796
            },
            {
              "color": {
                "red": 136,
                "green": 112,
                "blue": 92
              },
              "score": 0.0077370196,
              "pixelFraction": 0.0071879383
            },
            {
              "color": {
                "red": 85,
                "green": 82,
                "blue": 76
              },
              "score": 0.006339986,
              "pixelFraction": 0.006837307
            },
            {
              "color": {
                "red": 70,
                "green": 41,
                "blue": 25
              },
              "score": 0.006085202,
              "pixelFraction": 0.0039446005
            }
          ]
        }
      },
      "cropHintsAnnotation": {
        "cropHints": [
          {
            "boundingPoly": {
              "vertices": [
                {},
                {
                  "x": 295
                },
                {
                  "x": 295,
                  "y": 399
                },
                {
                  "y": 399
                }
              ]
            },
            "confidence": 1,
            "importanceFraction": 1.1899999
          }
        ]
      },
      "fullTextAnnotation": {
        "pages": [
          {
            "property": {
              "detectedLanguages": [
                {
                  "languageCode": "ko"
                }
              ]
            },
            "width": 296,
            "height": 400,
            "blocks": [
              {
                "property": {
                  "detectedLanguages": [
                    {
                      "languageCode": "en"
                    }
                  ]
                },
                "boundingBox": {
                  "vertices": [
                    {
                      "x": 21,
                      "y": 11
                    },
                    {
                      "x": 33,
                      "y": 11
                    },
                    {
                      "x": 33,
                      "y": 16
                    },
                    {
                      "x": 21,
                      "y": 16
                    }
                  ]
                },
                "paragraphs": [
                  {
                    "property": {
                      "detectedLanguages": [
                        {
                          "languageCode": "en"
                        }
                      ]
                    },
                    "boundingBox": {
                      "vertices": [
                        {
                          "x": 21,
                          "y": 11
                        },
                        {
                          "x": 33,
                          "y": 11
                        },
                        {
                          "x": 33,
                          "y": 16
                        },
                        {
                          "x": 21,
                          "y": 16
                        }
                      ]
                    },
                    "words": [
                      {
                        "property": {
                          "detectedLanguages": [
                            {
                              "languageCode": "en"
                            }
                          ]
                        },
                        "boundingBox": {
                          "vertices": [
                            {
                              "x": 21,
                              "y": 11
                            },
                            {
                              "x": 33,
                              "y": 11
                            },
                            {
                              "x": 33,
                              "y": 16
                            },
                            {
                              "x": 21,
                              "y": 16
                            }
                          ]
                        },
                        "symbols": [
                          {
                            "property": {
                              "detectedLanguages": [
                                {
                                  "languageCode": "ko"
                                }
                              ]
                            },
                            "boundingBox": {
                              "vertices": [
                                {
                                  "x": 21,
                                  "y": 11
                                },
                                {
                                  "x": 26,
                                  "y": 11
                                },
                                {
                                  "x": 26,
                                  "y": 16
                                },
                                {
                                  "x": 21,
                                  "y": 16
                                }
                              ]
                            },
                            "text": "T"
                          },
                          {
                            "property": {
                              "detectedLanguages": [
                                {
                                  "languageCode": "ko"
                                }
                              ]
                            },
                            "boundingBox": {
                              "vertices": [
                                {
                                  "x": 29,
                                  "y": 11
                                },
                                {
                                  "x": 30,
                                  "y": 11
                                },
                                {
                                  "x": 30,
                                  "y": 15
                                },
                                {
                                  "x": 29,
                                  "y": 15
                                }
                              ]
                            },
                            "text": "r"
                          },
                          {
                            "property": {
                              "detectedLanguages": [
                                {
                                  "languageCode": "ko"
                                }
                              ],
                              "detectedBreak": {
                                "type": "EOL_SURE_SPACE"
                              }
                            },
                            "boundingBox": {
                              "vertices": [
                                {
                                  "x": 33,
                                  "y": 12
                                },
                                {
                                  "x": 33,
                                  "y": 12
                                },
                                {
                                  "x": 33,
                                  "y": 15
                                },
                                {
                                  "x": 33,
                                  "y": 15
                                }
                              ]
                            },
                            "text": "i"
                          }
                        ]
                      }
                    ]
                  }
                ],
                "blockType": "TEXT"
              },
              {
                "property": {
                  "detectedLanguages": [
                    {
                      "languageCode": "ko"
                    }
                  ]
                },
                "boundingBox": {
                  "vertices": [
                    {
                      "x": 277,
                      "y": 9
                    },
                    {
                      "x": 283,
                      "y": 9
                    },
                    {
                      "x": 283,
                      "y": 16
                    },
                    {
                      "x": 277,
                      "y": 16
                    }
                  ]
                },
                "paragraphs": [
                  {
                    "property": {
                      "detectedLanguages": [
                        {
                          "languageCode": "ko"
                        }
                      ]
                    },
                    "boundingBox": {
                      "vertices": [
                        {
                          "x": 277,
                          "y": 9
                        },
                        {
                          "x": 283,
                          "y": 9
                        },
                        {
                          "x": 283,
                          "y": 16
                        },
                        {
                          "x": 277,
                          "y": 16
                        }
                      ]
                    },
                    "words": [
                      {
                        "property": {
                          "detectedLanguages": [
                            {
                              "languageCode": "ko"
                            }
                          ]
                        },
                        "boundingBox": {
                          "vertices": [
                            {
                              "x": 277,
                              "y": 9
                            },
                            {
                              "x": 283,
                              "y": 9
                            },
                            {
                              "x": 283,
                              "y": 16
                            },
                            {
                              "x": 277,
                              "y": 16
                            }
                          ]
                        },
                        "symbols": [
                          {
                            "property": {
                              "detectedLanguages": [
                                {
                                  "languageCode": "ko"
                                }
                              ],
                              "detectedBreak": {
                                "type": "EOL_SURE_SPACE"
                              }
                            },
                            "boundingBox": {
                              "vertices": [
                                {
                                  "x": 277,
                                  "y": 9
                                },
                                {
                                  "x": 283,
                                  "y": 9
                                },
                                {
                                  "x": 283,
                                  "y": 16
                                },
                                {
                                  "x": 277,
                                  "y": 16
                                }
                              ]
                            },
                            "text": "낚"
                          }
                        ]
                      }
                    ]
                  }
                ],
                "blockType": "TEXT"
              }
            ]
          }
        ],
        "text": "Tri\n낚\n"
      },
      "webDetection": {
        "webEntities": [
          {
            "entityId": "/m/05l1t9",
            "score": 14.6564,
            "description": "Andrea Solari"
          },
          {
            "entityId": "/m/0b2_mh",
            "score": 2.12848,
            "description": "Pinacoteca di Brera"
          },
          {
            "entityId": "/m/073z19",
            "score": 1.25536,
            "description": "Thyssen-Bornemisza Museum"
          },
          {
            "entityId": "/m/01dv4h",
            "score": 1.0198215,
            "description": "Portrait"
          },
          {
            "entityId": "/g/11bxc5__2n",
            "score": 0.8668,
            "description": "Portrait of Tommaso Raimondi"
          }
        ],
        "fullMatchingImages": [
          {
            "url": "http://upload.wikimedia.org/wikipedia/commons/1/1d/Amico_Aspertini_-_Portrait_of_Tommaso_Raimondi_-_WGA1022.jpg"
          },
          {
            "url": "https://s-media-cache-ak0.pinimg.com/736x/8c/6b/cc/8c6bcc4b8831dabb08447bf35a0a0b91.jpg"
          },
          {
            "url": "https://s-media-cache-ak0.pinimg.com/736x/54/64/15/54641582bdc26b0b40687030c202ef61.jpg"
          },
          {
            "url": "http://portraittimeline.com/1500s%20Portraits%20-%20f_files/image021.jpg"
          }
        ],
        "partialMatchingImages": [
          {
            "url": "https://imagenes.museothyssen.org/sites/default/files/imagen/obras/1928.4_retrato-tommaso-raimondi.jpg"
          },
          {
            "url": "https://upload.wikimedia.org/wikipedia/commons/b/b0/Amico_Aspertini_-_Retrato_de_Tommaso_Raimondi.jpg"
          },
          {
            "url": "https://imagenes.museothyssen.org/sites/default/files/styles/16x9_large/public/imagen/obras/1928.4_retrato-tommaso-raimondi.jpg?itok=Fpr3hDFX"
          },
          {
            "url": "http://upyourpic.org/images/201405/552ibcwlf5.jpg"
          },
          {
            "url": "https://farm2.staticflickr.com/1692/26120341571_0b259c2586_b.jpg"
          }
        ],
        "pagesWithMatchingImages": [
          {
            "url": "https://www.pinterest.com/pin/557390891361741764/"
          },
          {
            "url": "https://it.pinterest.com/ferdinandaramos/andrea-solario-1460-1524/"
          },
          {
            "url": "https://fr.pinterest.com/pin/418412621609993598/"
          },
          {
            "url": "https://www.pinterest.com/RyszKrzysz/solario/"
          },
          {
            "url": "https://www.pinterest.com/pin/478155685415613157/"
          }
        ],
        "visuallySimilarImages": [
          {
            "url": "https://s-media-cache-ak0.pinimg.com/736x/54/64/15/54641582bdc26b0b40687030c202ef61.jpg"
          },
          {
            "url": "https://s-media-cache-ak0.pinimg.com/236x/c9/e3/ee/c9e3ee5024f6b690a3ecfd93482e84c4.jpg"
          },
          {
            "url": "https://s-media-cache-ak0.pinimg.com/564x/0a/e9/6c/0ae96c7bfdd5079395482a110353873e.jpg"
          },
          {
            "url": "https://s-media-cache-ak0.pinimg.com/originals/54/a4/70/54a470ed53eabbc58d5ed527ec6dcb91.jpg"
          },
          {
            "url": "https://s-media-cache-ak0.pinimg.com/236x/f3/37/9a/f3379a52d5c40afc9e4fdbff9eb1978a.jpg"
          }
        ]
      }
    }
  ]
}
